scruffy/__init__.py
scruffy/config.py
scruffy/env.py
scruffy/file.py
scruffy/plugin.py
scruffy/state.py
scruffington-0.3.9.dist-info/LICENSE
scruffington-0.3.9.dist-info/METADATA
scruffington-0.3.9.dist-info/WHEEL
scruffington-0.3.9.dist-info/top_level.txt
scruffington-0.3.9.dist-info/RECORD
