Metadata-Version: 2.2
Name: scruffington
Version: 0.3.9
Summary: The janitor
Home-page: https://github.com/snare/scruffy
Author: snare
Author-email: snare@ho.ax
License: MIT
Keywords: scruffy
License-File: LICENSE
Requires-Dist: pyyaml
Requires-Dist: six
Dynamic: author
Dynamic: author-email
Dynamic: description
Dynamic: description-content-type
Dynamic: home-page
Dynamic: keywords
Dynamic: license
Dynamic: requires-dist
Dynamic: summary
